benchmarks/__init__.py
benchmarks/benchmark_csv_parquet.py
benchmarks/benchmark_pandas_polars.py
income_predict_d100_d400/__init__.py
income_predict_d100_d400/cleaning.py
income_predict_d100_d400/data.py
income_predict_d100_d400/evaluation.py
income_predict_d100_d400/feature_engineering.py
income_predict_d100_d400/model_training.py
income_predict_d100_d400/pipeline.py
income_predict_d100_d400/pipeline_summary.py
income_predict_d100_d400/plotting.py
income_predict_d100_d400/robust_paths.py
income_predict_d100_d400/eda/__init__.py
income_predict_d100_d400/eda/plots.py
income_predict_d100_d400/eda/preprocessing.py
income_predict_d100_d400/final_report/__init__.py
income_predict_d100_d400/final_report/plots.py
tests/__init__.py
tests/test_cleaning.py
tests/test_feature_engineering.py
income_predict_d100_d400-1.0.0.dist-info/METADATA
income_predict_d100_d400-1.0.0.dist-info/WHEEL
income_predict_d100_d400-1.0.0.dist-info/top_level.txt
income_predict_d100_d400-1.0.0.dist-info/RECORD
