Metadata-Version: 2.4
Name: income_predict_d100_d400
Version: 1.0.0
Summary: My installable package for income prediction
License: MIT
Requires-Python: >=3.12
Requires-Dist: ucimlrepo==0.0.7
Requires-Dist: numpy==2.3.5
Requires-Dist: polars==1.34.0
Requires-Dist: pyarrow==21.0.0
Requires-Dist: matplotlib==3.10.7
Requires-Dist: seaborn==0.13.2
Requires-Dist: scikit-learn==1.7.2
Requires-Dist: lightgbm==4.6.0
Requires-Dist: scipy==1.16.3
